open_close_mixin/__about__.py
open_close_mixin/__init__.py
open_close_mixin/constants.py
open_close_mixin/decorators.py
open_close_mixin/open_close_mixin.py
open_close_mixin-1.1.3.dist-info/LICENSE
open_close_mixin-1.1.3.dist-info/METADATA
open_close_mixin-1.1.3.dist-info/WHEEL
open_close_mixin-1.1.3.dist-info/top_level.txt
open_close_mixin-1.1.3.dist-info/RECORD
