Metadata-Version: 2.1
Name: open-close-mixin
Version: 1.1.3
Summary: Easy plugin for open-close class objects
Home-page: https://github.com/CarlosAdp/open-close-mixin
Author: Carlos Alberto Duarte Pinto
Author-email: carlos.adpinto@gmail.com
License: MIT
Download-URL: https://github.com/CarlosAdp/open-close-mixin/archive/v1.1.3.tar.gz
Keywords: plugin,mixin,decorator
Platform: UNKNOWN
Classifier: Programming Language :: Python :: 3.8
Classifier: Programming Language :: Python :: 3.9
Classifier: Operating System :: OS Independent
Classifier: Topic :: Utilities
Classifier: License :: OSI Approved :: MIT License
Classifier: Intended Audience :: Developers
